{
  "version": "1.1",
  "created_at": "2025-09-08 10:37:34",
  "source_size": {
    "w": 640,
    "h": 480
  },
  "people": [
    {
      "slot": 0,
      "bbox_px": {
        "x": 54,
        "y": 104,
        "w": 275,
        "h": 344
      },
      "bbox": {
        "x": 0.084375,
        "y": 0.21666666666666667,
        "w": 0.4296875,
        "h": 0.7166666666666667
      },
      "keypoints_px": [
        {
          "name": "nose",
          "x": 216.5885009765625,
          "y": 125.06596374511719,
          "score": 0.9968109726905823
        },
        {
          "name": "left_eye",
          "x": 237.38377380371094,
          "y": 106.40852355957031,
          "score": 0.9816231727600098
        },
        {
          "name": "right_eye",
          "x": 191.56021118164062,
          "y": 104.27729797363281,
          "score": 0.990336537361145
        },
        {
          "name": "left_ear",
          "x": 263.5458068847656,
          "y": 125.25050354003906,
          "score": 0.5738256573677063
        },
        {
          "name": "right_ear",
          "x": 160.690185546875,
          "y": 121.08233642578125,
          "score": 0.8653843998908997
        },
        {
          "name": "left_shoulder",
          "x": 269.9194641113281,
          "y": 252.12376403808594,
          "score": 0.9867473840713501
        },
        {
          "name": "right_shoulder",
          "x": 108.40828704833984,
          "y": 192.63160705566406,
          "score": 0.9558953642845154
        },
        {
          "name": "left_elbow",
          "x": 262.72698974609375,
          "y": 430.9549560546875,
          "score": 0.9085747599601746
        },
        {
          "name": "right_elbow",
          "x": 114.25479888916016,
          "y": 283.91021728515625,
          "score": 0.8542929291725159
        },
        {
          "name": "left_wrist",
          "x": 328.9460754394531,
          "y": 377.3175354003906,
          "score": 0.948891282081604
        },
        {
          "name": "right_wrist",
          "x": 272.3968200683594,
          "y": 216.9935302734375,
          "score": 0.9350093007087708
        },
        {
          "name": "left_hip",
          "x": 166.1507568359375,
          "y": 448.066162109375,
          "score": 0.19185365736484528
        },
        {
          "name": "right_hip",
          "x": 53.738494873046875,
          "y": 431.94732666015625,
          "score": 0.13229230046272278
        },
        {
          "name": "left_knee",
          "x": 296.9898681640625,
          "y": 329.12432861328125,
          "score": 0.03256381303071976
        },
        {
          "name": "right_knee",
          "x": 150.13018798828125,
          "y": 299.1175537109375,
          "score": 0.029991986230015755
        },
        {
          "name": "left_ankle",
          "x": 295.6684875488281,
          "y": 419.59259033203125,
          "score": 0.008446901105344296
        },
        {
          "name": "right_ankle",
          "x": 161.8673095703125,
          "y": 381.61175537109375,
          "score": 0.007373953703790903
        }
      ],
      "keypoints": [
        {
          "name": "nose",
          "x": 0.3384195327758789,
          "y": 0.2605540911356608
        },
        {
          "name": "left_eye",
          "x": 0.37091214656829835,
          "y": 0.22168442408243816
        },
        {
          "name": "right_eye",
          "x": 0.2993128299713135,
          "y": 0.2172443707784017
        },
        {
          "name": "left_ear",
          "x": 0.4117903232574463,
          "y": 0.26093854904174807
        },
        {
          "name": "right_ear",
          "x": 0.2510784149169922,
          "y": 0.25225486755371096
        },
        {
          "name": "left_shoulder",
          "x": 0.4217491626739502,
          "y": 0.5252578417460124
        },
        {
          "name": "right_shoulder",
          "x": 0.16938794851303102,
          "y": 0.4013158480326335
        },
        {
          "name": "left_elbow",
          "x": 0.4105109214782715,
          "y": 0.8978228251139323
        },
        {
          "name": "right_elbow",
          "x": 0.17852312326431274,
          "y": 0.5914796193440756
        },
        {
          "name": "left_wrist",
          "x": 0.5139782428741455,
          "y": 0.7860781987508138
        },
        {
          "name": "right_wrist",
          "x": 0.42562003135681153,
          "y": 0.4520698547363281
        },
        {
          "name": "left_hip",
          "x": 0.25961055755615237,
          "y": 0.9334711710611979
        },
        {
          "name": "right_hip",
          "x": 0.08396639823913574,
          "y": 0.8998902638753256
        },
        {
          "name": "left_knee",
          "x": 0.46404666900634767,
          "y": 0.6856756846110026
        },
        {
          "name": "right_knee",
          "x": 0.23457841873168944,
          "y": 0.6231615702311198
        },
        {
          "name": "left_ankle",
          "x": 0.46198201179504395,
          "y": 0.8741512298583984
        },
        {
          "name": "right_ankle",
          "x": 0.2529176712036133,
          "y": 0.7950244903564453
        }
      ],
      "score": 0.8359655737876892
    },
    {
      "slot": 1,
      "bbox_px": {
        "x": 354,
        "y": 135,
        "w": 269,
        "h": 332
      },
      "bbox": {
        "x": 0.553125,
        "y": 0.28125,
        "w": 0.4203125,
        "h": 0.6916666666666667
      },
      "keypoints_px": [
        {
          "name": "nose",
          "x": 422.3350830078125,
          "y": 157.91217041015625,
          "score": 0.9918394088745117
        },
        {
          "name": "left_eye",
          "x": 436.1629943847656,
          "y": 135.32041931152344,
          "score": 0.9842788577079773
        },
        {
          "name": "right_eye",
          "x": 398.29022216796875,
          "y": 142.587646484375,
          "score": 0.9691283106803894
        },
        {
          "name": "left_ear",
          "x": 465.62188720703125,
          "y": 138.80812072753906,
          "score": 0.8886386752128601
        },
        {
          "name": "right_ear",
          "x": 376.4648742675781,
          "y": 158.46942138671875,
          "score": 0.6779809594154358
        },
        {
          "name": "left_shoulder",
          "x": 524.6445922851562,
          "y": 214.34072875976562,
          "score": 0.9923302531242371
        },
        {
          "name": "right_shoulder",
          "x": 366.6922912597656,
          "y": 254.75177001953125,
          "score": 0.9836803674697876
        },
        {
          "name": "left_elbow",
          "x": 528.3607177734375,
          "y": 303.52490234375,
          "score": 0.9556783437728882
        },
        {
          "name": "right_elbow",
          "x": 353.6272888183594,
          "y": 404.9373779296875,
          "score": 0.8766592144966125
        },
        {
          "name": "left_wrist",
          "x": 437.946044921875,
          "y": 225.71145629882812,
          "score": 0.905547559261322
        },
        {
          "name": "right_wrist",
          "x": 386.1452331542969,
          "y": 371.511474609375,
          "score": 0.8417324423789978
        },
        {
          "name": "left_hip",
          "x": 556.072509765625,
          "y": 431.6255798339844,
          "score": 0.8006642460823059
        },
        {
          "name": "right_hip",
          "x": 439.130615234375,
          "y": 445.6602783203125,
          "score": 0.7529621124267578
        },
        {
          "name": "left_knee",
          "x": 607.25732421875,
          "y": 465.85791015625,
          "score": 0.048044729977846146
        },
        {
          "name": "right_knee",
          "x": 414.2825622558594,
          "y": 452.50933837890625,
          "score": 0.036073386669158936
        },
        {
          "name": "left_ankle",
          "x": 622.271240234375,
          "y": 466.9464111328125,
          "score": 0.0037136059254407883
        },
        {
          "name": "right_ankle",
          "x": 434.888427734375,
          "y": 421.94921875,
          "score": 0.0032795630395412445
        }
      ],
      "keypoints": [
        {
          "name": "nose",
          "x": 0.6598985671997071,
          "y": 0.3289836883544922
        },
        {
          "name": "left_eye",
          "x": 0.6815046787261962,
          "y": 0.2819175402323405
        },
        {
          "name": "right_eye",
          "x": 0.6223284721374511,
          "y": 0.2970575968424479
        },
        {
          "name": "left_ear",
          "x": 0.7275341987609864,
          "y": 0.2891835848490397
        },
        {
          "name": "right_ear",
          "x": 0.5882263660430909,
          "y": 0.3301446278889974
        },
        {
          "name": "left_shoulder",
          "x": 0.8197571754455566,
          "y": 0.4465431849161784
        },
        {
          "name": "right_shoulder",
          "x": 0.5729567050933838,
          "y": 0.5307328542073567
        },
        {
          "name": "left_elbow",
          "x": 0.825563621520996,
          "y": 0.6323435465494792
        },
        {
          "name": "right_elbow",
          "x": 0.5525426387786865,
          "y": 0.8436195373535156
        },
        {
          "name": "left_wrist",
          "x": 0.6842906951904297,
          "y": 0.4702322006225586
        },
        {
          "name": "right_wrist",
          "x": 0.6033519268035888,
          "y": 0.7739822387695312
        },
        {
          "name": "left_hip",
          "x": 0.868863296508789,
          "y": 0.8992199579874675
        },
        {
          "name": "right_hip",
          "x": 0.6861415863037109,
          "y": 0.9284589131673177
        },
        {
          "name": "left_knee",
          "x": 0.9488395690917969,
          "y": 0.9705373128255208
        },
        {
          "name": "right_knee",
          "x": 0.6473165035247803,
          "y": 0.942727788289388
        },
        {
          "name": "left_ankle",
          "x": 0.9722988128662109,
          "y": 0.9728050231933594
        },
        {
          "name": "right_ankle",
          "x": 0.6795131683349609,
          "y": 0.8790608723958333
        }
      ],
      "score": 0.7299988269805908
    }
  ]
}